calculadora_jfmatta/__init__.py
calculadora_jfmatta/calculadora.py
calculadora_jfmatta-0.0.3.dist-info/LICENSE
calculadora_jfmatta-0.0.3.dist-info/METADATA
calculadora_jfmatta-0.0.3.dist-info/WHEEL
calculadora_jfmatta-0.0.3.dist-info/top_level.txt
calculadora_jfmatta-0.0.3.dist-info/RECORD
