Metadata-Version: 2.1
Name: calculadora-jfmatta
Version: 0.0.3
Summary: Cálculos simples
Home-page: https://github.com/JulianoMata/calculadora
Author: JulianoMata
Author-email: jfmatta@gmail.com
Requires-Python: >=3.6
License-File: LICENSE
